{
  "title": "Acer Swift 5 (2022) hands-on: A beautiful laptop with a 16:10 display",
  "url": "https://www.xda-developers.com/acer-swift-5-2022-hands-on/",
  "date": "Sat, 21 May 2022 15:00:21 +0000",
  "content": "<p>At  MWC 2022, Acer introduced two new laptops: The Swift 3 and the more premium Swift 5. After having the chance to try out the Acer Swift 3 a couple of weeks ago, Acer also sent me the Acer Swift 5 so I could take a closer look at it. To be clear, this is</p><p>The post <a rel=\"nofollow\" href=\"https://www.xda-developers.com/acer-swift-5-2022-hands-on/\">Acer Swift 5 (2022) hands-on: A beautiful laptop with a 16:10 display</a> appeared first on <a rel=\"nofollow\" href=\"https://www.xda-developers.com\">XDA</a>.</p>",
  "image": "https://www.xda-developers.com/files/2022/05/Acer-Swift-5-2022-14.jpg",
  "description": "The 2022 Acer Swift 5 packs a taller 16:10 display and Intel's P-series processors into a stunning chassis. Here are our early impressions.",
  "publisher": "XDA Developers",
  "publisherUrl": "https://www.xda-developers.com/feed/"
}