{
  "title": "German finance chief calls for more fiscal discipline across EU - POLITICO Europe",
  "url": "https://www.politico.eu/article/germany-finance-minister-christian-lindner-more-fiscal-discipline-eu/",
  "date": "Sun, 22 May 2022 10:25:59 GMT",
  "content": "<a href=\"https://www.politico.eu/article/germany-finance-minister-christian-lindner-more-fiscal-discipline-eu/\" target=\"_blank\">German finance chief calls for more fiscal discipline across EU</a>&nbsp;&nbsp;<font color=\"#6f6f6f\">POLITICO Europe</font>",
  "image": "https://www.politico.eu/cdn-cgi/image/width=1200,height=630,fit=crop,quality=80,onerror=redirect/wp-content/uploads/2022/05/22/GettyImages-1240785291-scaled.jpg",
  "description": "There is a ‘real danger of stagflation,’ Lindner tells the FT.",
  "publisher": "Google News Finance USA",
  "publisherUrl": "https://news.google.com/search?q=finance&hl=en-US&gl=US&ceid=US:en"
}